ke/__init__.py
ke-0.0.7.dist-info/licenses/LICENSE
ke-0.0.7.dist-info/METADATA
ke-0.0.7.dist-info/WHEEL
ke-0.0.7.dist-info/top_level.txt
ke-0.0.7.dist-info/RECORD
