Metadata-Version: 2.4
Name: ke
Version: 0.0.7
Summary: File access utils
Home-page: https://github.com/t-c-w/ke
Author: Thor Whalen
License: apache-2.0
Platform: any
License-File: LICENSE
Dynamic: license-file
